{"paths":{},"types":[],"uuids":["0cBuios3lDkogLdW5tqbrp","12FmbMq3lDLrRnBKzOVf7U","3eXo8pgidE7YsgHScBFnfs","63ITy333lF/YR8HFDXCR6H","984e7NuC1NFb94FxPb22Jx","9bjueQbNpGo50X+rju++zY","abOQMfZulNx7mXHPOA3gCM","b2tVeo94VMpaLSaCq60lQU","d5DbEx2AZCu5QcvRN+328F","23nXsgwdhMgbjvy0qQu8LJ","4coPQuZTBGGYkB0BnkmjEr","5fgMHgS3VOIoYU/pnS0boZ","67V25RDwFHepJU2v1Px6AG","81t9/DhU5MapC6REGDKErf","9dvbEKTalB14Dmo3KIVQfk","ccmxGcu9hBvYmbHY2dubKO","e1pbn1tGtCQr28gIUPX8rs","ecpdLyjvZBwrvm+cedCcQy","f0A7G6wEtNQ75s9OJ4RxL4"],"scenes":{"db://assets/BirdFly.fire":0},"redirect":[17,0],"deps":["internal"],"packs":{"0607cc345":[0,9,10,11,12,13,14,15,16,18],"0645c3929":[1,2,3,4,5,6,7,8]},"name":"main","importBase":"import","nativeBase":"native","debug":false,"isZip":false,"encrypted":false,"versions":{"import":["0607cc345","37dea","0645c3929","fc990"],"native":[1,"077bf",2,"077bf",3,"28b45",4,"7e59b",5,"ab915",6,"4fd39",7,"a71b7",8,"08888"]}}